{
  "sections": {
    "main": {
      "type": "main-product",
      "blocks": {
        "tb1": { "type": "trust_badge", "settings": { "icon": "shipping", "text": "Free Shipping" } },
        "tb2": { "type": "trust_badge", "settings": { "icon": "returns", "text": "30-Day Returns" } },
        "tb3": { "type": "trust_badge", "settings": { "icon": "warranty", "text": "Lifetime Warranty" } },
        "acc1": { "type": "accordion", "settings": { "title": "Description", "open": true } },
        "acc2": { "type": "accordion", "settings": { "title": "Specifications" } },
        "acc3": { "type": "accordion", "settings": { "title": "Shipping & Returns" } }
      },
      "block_order": ["tb1", "tb2", "tb3", "acc1", "acc2", "acc3"],
      "settings": {}
    }
  },
  "order": ["main"]
}
